{"RandomPaperID":770,"Questions":[{"QuestionID":39,"QuestionType":"禁毒知识","Content":"从毒品对人的中枢神经的作用看，可分为抑制剂、致幻剂和兴奋剂等，其中属于抑制剂的毒品种类是（  ）。","Score":5,"Options":[{"Sign":"A","Content":"巴比妥类"},{"Sign":"B","Content":"苯丙胺类"},{"Sign":"C","Content":"麦司卡林"},{"Sign":"D","Content":"LSD"}]},{"QuestionID":285,"QuestionType":"禁毒知识","Content":"吸毒是违法行为。（  ）","Score":5,"Options":[{"Sign":"A","Content":"正确"},{"Sign":"B","Content":"错误"}]},{"QuestionID":237,"QuestionType":"禁毒知识","Content":"（）是被滥用最早的毒品，历史悠久，地域广泛，滥用者众多。","Score":5,"Options":[{"Sign":"A","Content":"可卡因"},{"Sign":"B","Content":"阿片类毒品"},{"Sign":"C","Content":"苯丙胺类兴奋剂"},{"Sign":"D","Content":"大麻"}]},{"QuestionID":49,"QuestionType":"禁毒知识","Content":"不满十六周岁的未成年人吸毒成瘾严重的，可以不适用(  )。","Score":5,"Options":[{"Sign":"A","Content":"强制隔离戒毒"},{"Sign":"B","Content":"责令其接受社区戒毒"},{"Sign":"C","Content":"责令其接受社区康复"},{"Sign":"D","Content":"自愿戒毒"}]},{"QuestionID":98,"QuestionType":"禁毒知识","Content":"国家确定的麻醉药品药用原植物种植企业的提取加工场所，以及国家设立的麻醉药品储存仓库，列为（  ）。","Score":5,"Options":[{"Sign":"A","Content":"国家重点工程"},{"Sign":"B","Content":"国家禁区"},{"Sign":"C","Content":"国家重点警戒目标"},{"Sign":"D","Content":"保密单位"}]},{"QuestionID":315,"QuestionType":"禁毒知识","Content":"下列选项中属于禁毒志愿者义务的是。（  ）","Score":5,"Options":[{"Sign":"A","Content":"履行禁毒志愿者服务承诺"},{"Sign":"B","Content":"自身远离毒品"},{"Sign":"C","Content":"每年参加不少于48小时禁毒志愿服务活动"},{"Sign":"D","Content":"以上选项都是"}]},{"QuestionID":283,"QuestionType":"禁毒知识","Content":"吸毒如果仅仅偶尔吸一两次，一般都不会上瘾。这种说法（  ）","Score":5,"Options":[{"Sign":"A","Content":"正确"},{"Sign":"B","Content":"错误"}]},{"QuestionID":359,"QuestionType":"禁毒知识","Content":"以下几种毒品，成瘾性和毒副作用最强的是（　）。","Score":5,"Options":[{"Sign":"A","Content":"古柯叶"},{"Sign":"B","Content":"海洛因"},{"Sign":"C","Content":"鸦片"},{"Sign":"D","Content":"大麻"}]},{"QuestionID":224,"QuestionType":"禁毒知识","Content":"止咳水通常含有可待因、麻黄碱等成分，（ ）服用可形成心理依赖，戒断症状类似海洛因毒品。","Score":5,"Options":[{"Sign":"A","Content":"长期大量"},{"Sign":"B","Content":"B遵医嘱"},{"Sign":"C","Content":"按药品说明计量服用"},{"Sign":"D","Content":"一次过量服用"}]},{"QuestionID":392,"QuestionType":"禁毒知识","Content":"孕妇涉毒犯罪有可能免除刑责。","Score":5,"Options":[{"Sign":"A","Content":"正确"},{"Sign":"B","Content":"错误"}]},{"QuestionID":297,"QuestionType":"禁毒知识","Content":"吸食过量大麻可发生意识不清、产生幻觉等。","Score":5,"Options":[{"Sign":"A","Content":"正确"},{"Sign":"B","Content":"错误"}]},{"QuestionID":280,"QuestionType":"禁毒知识","Content":"吸毒人员可以自行到具有戒毒治疗资质的医疗机构接受戒毒治疗。以上说法正确吗？（  ）","Score":5,"Options":[{"Sign":"A","Content":"正确"},{"Sign":"B","Content":"错误"}]},{"QuestionID":126,"QuestionType":"禁毒知识","Content":"李某发现儿子小强吸毒后，便将其关在家中，并与家人轮流看守令其戒毒。起初，断了毒品的小强呼天喊地，半个月后，小强又恢复了正常。试问小强是否已全部戒除毒瘾？（  ）","Score":5,"Options":[{"Sign":"A","Content":"已完全戒断毒瘾"},{"Sign":"B","Content":"只戒断生理上毒瘾"}]},{"QuestionID":311,"QuestionType":"禁毒知识","Content":"下列说法正确的是 。（  ）","Score":5,"Options":[{"Sign":"A","Content":"吸毒成瘾是一种脑病"},{"Sign":"B","Content":"少量吸毒对身体没有损害"},{"Sign":"C","Content":"只吸几次毒不会上瘾"},{"Sign":"D","Content":"吸食合成毒品危害比较传统毒品要小"}]},{"QuestionID":95,"QuestionType":"禁毒知识","Content":"国家鼓励公民、组织开展公益性的禁毒宣传活动。","Score":5,"Options":[{"Sign":"A","Content":"正确"},{"Sign":"B","Content":"错误"}]},{"QuestionID":298,"QuestionType":"禁毒知识","Content":"吸食合成毒品危害比较传统毒品要小。","Score":5,"Options":[{"Sign":"A","Content":"正确"},{"Sign":"B","Content":"错误"}]},{"QuestionID":189,"QuestionType":"禁毒知识","Content":"吸食K粉、摇头丸等药物会导致血压上升、心跳过快、心律失常，甚至可能诱发精神分裂症及急性心脑疾病。但不会致人死亡。","Score":5,"Options":[{"Sign":"A","Content":"正确"},{"Sign":"B","Content":"错误"}]},{"QuestionID":33,"QuestionType":"禁毒知识","Content":"安纳咖，外观常为针剂，也有本色粉末状，长期使用会产生药物耐受性但不需要不断加大用药剂量。","Score":5,"Options":[{"Sign":"A","Content":"正确"},{"Sign":"B","Content":"错误"}]},{"QuestionID":214,"QuestionType":"禁毒知识","Content":"娱乐场所应当建立（ ）制度，发现娱乐场所内有毒品违法犯罪活动的，应当立即向公安机关报告。","Score":5,"Options":[{"Sign":"A","Content":"查验"},{"Sign":"B","Content":"监测"},{"Sign":"C","Content":"巡查"},{"Sign":"D","Content":"抽查"}]},{"QuestionID":168,"QuestionType":"禁毒知识","Content":"王某在自己开垦的山地里种植罂粟，收获前他学习了《禁毒法》，将所有罂粟铲除，对于王某应该（　） 。","Score":5,"Options":[{"Sign":"A","Content":"拘留"},{"Sign":"B","Content":"罚款"},{"Sign":"C","Content":"不予处罚"},{"Sign":"D","Content":"判刑"}]}]}